{
    "MNIST_0v1": [
        {
            "K": 2,
            "mean_acc": 0.88985,
            "std_acc": 0.10495762240066225,
            "mean_erank": 1.647128877705728,
            "S": 0.823564438852864,
            "marginal": 0.0
        },
        {
            "K": 3,
            "mean_acc": 0.9473499999999998,
            "std_acc": 0.05243665225774811,
            "mean_erank": 2.8840979395198163,
            "S": 0.9613659798399388,
            "marginal": 0.057499999999999774
        },
        {
            "K": 4,
            "mean_acc": 0.9592999999999999,
            "std_acc": 0.049119853419976746,
            "mean_erank": 3.7615480274703605,
            "S": 0.9403870068675901,
            "marginal": 0.011950000000000127
        },
        {
            "K": 6,
            "mean_acc": 0.9789999999999999,
            "std_acc": 0.01835755975068583,
            "mean_erank": 5.551816663932181,
            "S": 0.9253027773220301,
            "marginal": 0.01969999999999994
        },
        {
            "K": 8,
            "mean_acc": 0.9859,
            "std_acc": 0.014872457765951131,
            "mean_erank": 6.671709907455976,
            "S": 0.833963738431997,
            "marginal": 0.006900000000000128
        },
        {
            "K": 12,
            "mean_acc": 0.98705,
            "std_acc": 0.011019187810360624,
            "mean_erank": 9.135254029533803,
            "S": 0.7612711691278169,
            "marginal": 0.0011499999999999844
        },
        {
            "K": 16,
            "mean_acc": 0.99095,
            "std_acc": 0.00687186292063514,
            "mean_erank": 9.867352682787686,
            "S": 0.6167095426742304,
            "marginal": 0.0039000000000000146
        },
        {
            "K": 24,
            "mean_acc": 0.99405,
            "std_acc": 0.005217518567288478,
            "mean_erank": 11.988173884948601,
            "S": 0.4995072452061917,
            "marginal": 0.0030999999999999917
        },
        {
            "K": 32,
            "mean_acc": 0.9936999999999999,
            "std_acc": 0.004980963762164909,
            "mean_erank": 13.01952402099787,
            "S": 0.40686012565618346,
            "marginal": -0.0003500000000000725
        },
        {
            "K": 48,
            "mean_acc": 0.99495,
            "std_acc": 0.004372928080817248,
            "mean_erank": 14.764028402430121,
            "S": 0.30758392505062754,
            "marginal": 0.0012500000000000844
        },
        {
            "K": 64,
            "mean_acc": 0.9953500000000001,
            "std_acc": 0.0038733060813728607,
            "mean_erank": 15.724783556555012,
            "S": 0.24569974307117207,
            "marginal": 0.00040000000000006697
        },
        {
            "K": 128,
            "mean_acc": 0.9945500000000002,
            "std_acc": 0.005515659525387705,
            "mean_erank": 17.62404496538962,
            "S": 0.1376878512921064,
            "marginal": -0.0007999999999999119
        },
        {
            "K": 256,
            "mean_acc": 0.9959000000000002,
            "std_acc": 0.003345145736735543,
            "mean_erank": 20.400945744611416,
            "S": 0.07969119431488834,
            "marginal": 0.0013500000000000734
        },
        {
            "K": 512,
            "mean_acc": 0.9953000000000002,
            "std_acc": 0.0037960505792204624,
            "mean_erank": 23.34375513075433,
            "S": 0.045593271739754554,
            "marginal": -0.0006000000000000449
        },
        {
            "K": 1024,
            "mean_acc": 0.9967,
            "std_acc": 0.002521904042583697,
            "mean_erank": 26.939828650497848,
            "S": 0.026308426416501805,
            "marginal": 0.0013999999999998458
        },
        {
            "K": 2048,
            "mean_acc": 0.9968,
            "std_acc": 0.002740437921208942,
            "mean_erank": 29.82008193727355,
            "S": 0.01456058688343435,
            "marginal": 9.999999999998899e-05
        },
        {
            "K": 4096,
            "mean_acc": 0.9964000000000002,
            "std_acc": 0.003611094017053557,
            "mean_erank": 32.350310311404975,
            "S": 0.007898024978370355,
            "marginal": -0.0003999999999998449
        }
    ],
    "MNIST_3v8": [
        {
            "K": 2,
            "mean_acc": 0.6992500000000001,
            "std_acc": 0.09912649746662092,
            "mean_erank": 1.79794326571802,
            "S": 0.89897163285901,
            "marginal": 0.0
        },
        {
            "K": 3,
            "mean_acc": 0.76035,
            "std_acc": 0.07739995155037244,
            "mean_erank": 3.2847914932368774,
            "S": 1.0949304977456258,
            "marginal": 0.06109999999999982
        },
        {
            "K": 4,
            "mean_acc": 0.7968499999999998,
            "std_acc": 0.056618923515022776,
            "mean_erank": 4.450606568218507,
            "S": 1.1126516420546269,
            "marginal": 0.036499999999999866
        },
        {
            "K": 6,
            "mean_acc": 0.8250500000000001,
            "std_acc": 0.04661408049077017,
            "mean_erank": 6.558009158773525,
            "S": 1.0930015264622541,
            "marginal": 0.028200000000000225
        },
        {
            "K": 8,
            "mean_acc": 0.8416,
            "std_acc": 0.04425991414361306,
            "mean_erank": 8.34220260569765,
            "S": 1.0427753257122063,
            "marginal": 0.016549999999999954
        },
        {
            "K": 12,
            "mean_acc": 0.8605999999999999,
            "std_acc": 0.038924799292995714,
            "mean_erank": 10.588683322356522,
            "S": 0.8823902768630435,
            "marginal": 0.018999999999999906
        },
        {
            "K": 16,
            "mean_acc": 0.8722000000000001,
            "std_acc": 0.03254473843803326,
            "mean_erank": 12.921996887733702,
            "S": 0.8076248054833564,
            "marginal": 0.011600000000000166
        },
        {
            "K": 24,
            "mean_acc": 0.8734000000000001,
            "std_acc": 0.03331200984630018,
            "mean_erank": 16.773267065955555,
            "S": 0.6988861277481481,
            "marginal": 0.0011999999999999789
        },
        {
            "K": 32,
            "mean_acc": 0.8919000000000001,
            "std_acc": 0.023267788893661562,
            "mean_erank": 17.686700864596265,
            "S": 0.5527094020186333,
            "marginal": 0.018500000000000072
        },
        {
            "K": 48,
            "mean_acc": 0.89345,
            "std_acc": 0.024530032613105098,
            "mean_erank": 21.260923691824456,
            "S": 0.4429359102463428,
            "marginal": 0.0015499999999998293
        },
        {
            "K": 64,
            "mean_acc": 0.9000999999999999,
            "std_acc": 0.0232376849105069,
            "mean_erank": 22.524083776772063,
            "S": 0.3519388090120635,
            "marginal": 0.006649999999999934
        },
        {
            "K": 128,
            "mean_acc": 0.92035,
            "std_acc": 0.017471476754985546,
            "mean_erank": 25.85027902287533,
            "S": 0.20195530486621352,
            "marginal": 0.0202500000000001
        },
        {
            "K": 256,
            "mean_acc": 0.9276499999999999,
            "std_acc": 0.017954177786799367,
            "mean_erank": 28.92673543910488,
            "S": 0.11299506030900344,
            "marginal": 0.007299999999999862
        },
        {
            "K": 512,
            "mean_acc": 0.9490500000000001,
            "std_acc": 0.011925707526180563,
            "mean_erank": 31.16718528361141,
            "S": 0.060873408757053535,
            "marginal": 0.021400000000000197
        },
        {
            "K": 1024,
            "mean_acc": 0.9586999999999999,
            "std_acc": 0.01015184712256839,
            "mean_erank": 33.764781990491514,
            "S": 0.03297341991258937,
            "marginal": 0.009649999999999825
        },
        {
            "K": 2048,
            "mean_acc": 0.9651,
            "std_acc": 0.00667008245826093,
            "mean_erank": 35.4356541850971,
            "S": 0.017302565520066943,
            "marginal": 0.006400000000000072
        },
        {
            "K": 4096,
            "mean_acc": 0.9628999999999999,
            "std_acc": 0.009802550688468794,
            "mean_erank": 37.45392030109065,
            "S": 0.009144023511008459,
            "marginal": -0.0022000000000000908
        }
    ],
    "MNIST_4v9": [
        {
            "K": 2,
            "mean_acc": 0.6204,
            "std_acc": 0.05864801786931934,
            "mean_erank": 1.7871215296855771,
            "S": 0.8935607648427886,
            "marginal": 0.0
        },
        {
            "K": 3,
            "mean_acc": 0.6663499999999999,
            "std_acc": 0.07189090693543936,
            "mean_erank": 3.1923557999856915,
            "S": 1.0641185999952305,
            "marginal": 0.045949999999999935
        },
        {
            "K": 4,
            "mean_acc": 0.6944000000000001,
            "std_acc": 0.06485283339993714,
            "mean_erank": 4.3448177665958605,
            "S": 1.0862044416489651,
            "marginal": 0.02805000000000024
        },
        {
            "K": 6,
            "mean_acc": 0.74,
            "std_acc": 0.06667270805959512,
            "mean_erank": 5.889683494710221,
            "S": 0.9816139157850369,
            "marginal": 0.04559999999999986
        },
        {
            "K": 8,
            "mean_acc": 0.7685499999999998,
            "std_acc": 0.06384960845612132,
            "mean_erank": 7.263313129611093,
            "S": 0.9079141412013866,
            "marginal": 0.028549999999999853
        },
        {
            "K": 12,
            "mean_acc": 0.8151999999999999,
            "std_acc": 0.04577346392835045,
            "mean_erank": 10.241696208412575,
            "S": 0.8534746840343813,
            "marginal": 0.04665000000000008
        },
        {
            "K": 16,
            "mean_acc": 0.8394999999999999,
            "std_acc": 0.04270831300812524,
            "mean_erank": 11.44417721675592,
            "S": 0.715261076047245,
            "marginal": 0.02429999999999999
        },
        {
            "K": 24,
            "mean_acc": 0.8695,
            "std_acc": 0.027762384623803482,
            "mean_erank": 13.828730797634712,
            "S": 0.576197116568113,
            "marginal": 0.030000000000000138
        },
        {
            "K": 32,
            "mean_acc": 0.8724000000000001,
            "std_acc": 0.025719447894540816,
            "mean_erank": 15.63441480919616,
            "S": 0.48857546278738,
            "marginal": 0.0029000000000000137
        },
        {
            "K": 48,
            "mean_acc": 0.893,
            "std_acc": 0.02632964109136318,
            "mean_erank": 19.20239739789344,
            "S": 0.40004994578944664,
            "marginal": 0.02059999999999995
        },
        {
            "K": 64,
            "mean_acc": 0.8965500000000002,
            "std_acc": 0.022146613736641542,
            "mean_erank": 20.163248569446242,
            "S": 0.31505075889759754,
            "marginal": 0.003550000000000164
        },
        {
            "K": 128,
            "mean_acc": 0.9061,
            "std_acc": 0.023580500418778228,
            "mean_erank": 23.303265028955924,
            "S": 0.18205675803871815,
            "marginal": 0.009549999999999836
        },
        {
            "K": 256,
            "mean_acc": 0.92205,
            "std_acc": 0.015121921174242377,
            "mean_erank": 26.142711994293997,
            "S": 0.10211996872771092,
            "marginal": 0.01595000000000002
        },
        {
            "K": 512,
            "mean_acc": 0.9474000000000001,
            "std_acc": 0.010641428475538419,
            "mean_erank": 27.954928544197,
            "S": 0.054599469812884764,
            "marginal": 0.025350000000000095
        },
        {
            "K": 1024,
            "mean_acc": 0.9552,
            "std_acc": 0.010557461816175328,
            "mean_erank": 30.99190377455479,
            "S": 0.03026553102983866,
            "marginal": 0.007799999999999918
        },
        {
            "K": 2048,
            "mean_acc": 0.9568000000000001,
            "std_acc": 0.009500526301210906,
            "mean_erank": 33.10509000783978,
            "S": 0.016164594730390516,
            "marginal": 0.0016000000000000458
        },
        {
            "K": 4096,
            "mean_acc": 0.9562500000000002,
            "std_acc": 0.009646890690787373,
            "mean_erank": 35.59700151250184,
            "S": 0.008690674197388145,
            "marginal": -0.0005499999999999394
        }
    ],
    "MNIST_1v7": [
        {
            "K": 2,
            "mean_acc": 0.8360499999999998,
            "std_acc": 0.1030134578586701,
            "mean_erank": 1.6342477527756811,
            "S": 0.8171238763878406,
            "marginal": 0.0
        },
        {
            "K": 3,
            "mean_acc": 0.8792,
            "std_acc": 0.07014527781682812,
            "mean_erank": 2.8240587527348175,
            "S": 0.9413529175782726,
            "marginal": 0.04315000000000013
        },
        {
            "K": 4,
            "mean_acc": 0.8998,
            "std_acc": 0.07547158405651759,
            "mean_erank": 3.819801624272541,
            "S": 0.9549504060681353,
            "marginal": 0.020600000000000063
        },
        {
            "K": 6,
            "mean_acc": 0.9411499999999999,
            "std_acc": 0.0311055059434821,
            "mean_erank": 4.99309645473833,
            "S": 0.8321827424563883,
            "marginal": 0.04134999999999989
        },
        {
            "K": 8,
            "mean_acc": 0.9592500000000002,
            "std_acc": 0.017757040857079767,
            "mean_erank": 6.277078739939697,
            "S": 0.7846348424924621,
            "marginal": 0.018100000000000227
        },
        {
            "K": 12,
            "mean_acc": 0.9605499999999999,
            "std_acc": 0.016388181717323005,
            "mean_erank": 8.38684008409714,
            "S": 0.6989033403414283,
            "marginal": 0.0012999999999997458
        },
        {
            "K": 16,
            "mean_acc": 0.9558500000000001,
            "std_acc": 0.02675168219009788,
            "mean_erank": 9.523261757236458,
            "S": 0.5952038598272786,
            "marginal": -0.0046999999999998154
        },
        {
            "K": 24,
            "mean_acc": 0.9663499999999999,
            "std_acc": 0.01597818825774688,
            "mean_erank": 11.32486529285971,
            "S": 0.47186938720248794,
            "marginal": 0.010499999999999843
        },
        {
            "K": 32,
            "mean_acc": 0.9611999999999999,
            "std_acc": 0.017038485848220205,
            "mean_erank": 12.454987156152837,
            "S": 0.38921834862977617,
            "marginal": -0.005149999999999988
        },
        {
            "K": 48,
            "mean_acc": 0.9688,
            "std_acc": 0.013446560898608994,
            "mean_erank": 14.766232802021788,
            "S": 0.30762985004212057,
            "marginal": 0.007600000000000051
        },
        {
            "K": 64,
            "mean_acc": 0.9683499999999999,
            "std_acc": 0.014812241558926856,
            "mean_erank": 16.663789248928605,
            "S": 0.26037170701450946,
            "marginal": -0.00045000000000006146
        },
        {
            "K": 128,
            "mean_acc": 0.97485,
            "std_acc": 0.008908002020655366,
            "mean_erank": 20.438911283109732,
            "S": 0.15967899439929478,
            "marginal": 0.006500000000000061
        },
        {
            "K": 256,
            "mean_acc": 0.9809500000000001,
            "std_acc": 0.007695615634892383,
            "mean_erank": 23.58707786261428,
            "S": 0.09213702290083703,
            "marginal": 0.006100000000000105
        },
        {
            "K": 512,
            "mean_acc": 0.9816499999999999,
            "std_acc": 0.0066447347576859776,
            "mean_erank": 27.404689086812226,
            "S": 0.05352478337268013,
            "marginal": 0.0006999999999998119
        },
        {
            "K": 1024,
            "mean_acc": 0.98455,
            "std_acc": 0.007257582242041775,
            "mean_erank": 29.980941100284817,
            "S": 0.02927826279324689,
            "marginal": 0.0029000000000001247
        },
        {
            "K": 2048,
            "mean_acc": 0.9892,
            "std_acc": 0.004960846701924992,
            "mean_erank": 32.83715148602402,
            "S": 0.016033765374035166,
            "marginal": 0.004649999999999932
        },
        {
            "K": 4096,
            "mean_acc": 0.9934499999999999,
            "std_acc": 0.003836991008589935,
            "mean_erank": 34.55247310662364,
            "S": 0.008435662379546786,
            "marginal": 0.004249999999999976
        }
    ],
    "MNIST_2v7": [
        {
            "K": 2,
            "mean_acc": 0.8399500000000001,
            "std_acc": 0.08605302144608287,
            "mean_erank": 1.8454554295871923,
            "S": 0.9227277147935962,
            "marginal": 0.0
        },
        {
            "K": 3,
            "mean_acc": 0.87825,
            "std_acc": 0.05309955272881308,
            "mean_erank": 3.3170403670208786,
            "S": 1.1056801223402928,
            "marginal": 0.03829999999999989
        },
        {
            "K": 4,
            "mean_acc": 0.8963499999999998,
            "std_acc": 0.057430849723820045,
            "mean_erank": 4.760166612213842,
            "S": 1.1900416530534605,
            "marginal": 0.018099999999999783
        },
        {
            "K": 6,
            "mean_acc": 0.9177500000000002,
            "std_acc": 0.03611526685489116,
            "mean_erank": 6.83821795677067,
            "S": 1.1397029927951117,
            "marginal": 0.02140000000000042
        },
        {
            "K": 8,
            "mean_acc": 0.9173,
            "std_acc": 0.03935365294353245,
            "mean_erank": 8.635446976304607,
            "S": 1.0794308720380759,
            "marginal": -0.0004500000000001725
        },
        {
            "K": 12,
            "mean_acc": 0.9296000000000001,
            "std_acc": 0.025210910336598315,
            "mean_erank": 11.519586421396166,
            "S": 0.9599655351163472,
            "marginal": 0.012300000000000089
        },
        {
            "K": 16,
            "mean_acc": 0.92815,
            "std_acc": 0.02312363509485478,
            "mean_erank": 13.546375628178094,
            "S": 0.8466484767611309,
            "marginal": -0.0014500000000000624
        },
        {
            "K": 24,
            "mean_acc": 0.92935,
            "std_acc": 0.026808627342704432,
            "mean_erank": 17.353324648032928,
            "S": 0.7230551936680386,
            "marginal": 0.0011999999999999789
        },
        {
            "K": 32,
            "mean_acc": 0.935,
            "std_acc": 0.016347782724271807,
            "mean_erank": 20.015858164888208,
            "S": 0.6254955676527565,
            "marginal": 0.005650000000000044
        },
        {
            "K": 48,
            "mean_acc": 0.9364,
            "std_acc": 0.017650495743746122,
            "mean_erank": 21.311686322167933,
            "S": 0.4439934650451653,
            "marginal": 0.0013999999999999568
        },
        {
            "K": 64,
            "mean_acc": 0.9381499999999998,
            "std_acc": 0.0186668824392291,
            "mean_erank": 24.81236036862166,
            "S": 0.38769313075971346,
            "marginal": 0.0017499999999998073
        },
        {
            "K": 128,
            "mean_acc": 0.9518000000000002,
            "std_acc": 0.013398134198462117,
            "mean_erank": 27.267454196849812,
            "S": 0.21302698591288916,
            "marginal": 0.013650000000000384
        },
        {
            "K": 256,
            "mean_acc": 0.9554,
            "std_acc": 0.012483589227461785,
            "mean_erank": 29.63412951130782,
            "S": 0.11575831840354617,
            "marginal": 0.0035999999999998256
        },
        {
            "K": 512,
            "mean_acc": 0.9619,
            "std_acc": 0.009931767214348115,
            "mean_erank": 32.64642472167709,
            "S": 0.06376254828452557,
            "marginal": 0.00649999999999995
        },
        {
            "K": 1024,
            "mean_acc": 0.9777000000000001,
            "std_acc": 0.007966178506661781,
            "mean_erank": 34.3485274196385,
            "S": 0.03354348380824072,
            "marginal": 0.015800000000000147
        },
        {
            "K": 2048,
            "mean_acc": 0.98165,
            "std_acc": 0.005399305510896749,
            "mean_erank": 36.08410075900506,
            "S": 0.01761918982373294,
            "marginal": 0.003949999999999898
        },
        {
            "K": 4096,
            "mean_acc": 0.9843999999999999,
            "std_acc": 0.005398147830506312,
            "mean_erank": 37.76852401370987,
            "S": 0.009220831058034637,
            "marginal": 0.002749999999999919
        }
    ],
    "MNIST_4v7": [
        {
            "K": 2,
            "mean_acc": 0.7534000000000001,
            "std_acc": 0.10097618531119108,
            "mean_erank": 1.8237918168136966,
            "S": 0.9118959084068483,
            "marginal": 0.0
        },
        {
            "K": 3,
            "mean_acc": 0.8121999999999998,
            "std_acc": 0.07732664482570029,
            "mean_erank": 3.235503919424478,
            "S": 1.078501306474826,
            "marginal": 0.05879999999999974
        },
        {
            "K": 4,
            "mean_acc": 0.8480000000000001,
            "std_acc": 0.07443117626371358,
            "mean_erank": 4.573705917945527,
            "S": 1.1434264794863818,
            "marginal": 0.035800000000000276
        },
        {
            "K": 6,
            "mean_acc": 0.90145,
            "std_acc": 0.039655043815383685,
            "mean_erank": 6.312682722536375,
            "S": 1.052113787089396,
            "marginal": 0.053449999999999886
        },
        {
            "K": 8,
            "mean_acc": 0.9137,
            "std_acc": 0.03398249549400396,
            "mean_erank": 7.847698048644864,
            "S": 0.980962256080608,
            "marginal": 0.012249999999999983
        },
        {
            "K": 12,
            "mean_acc": 0.9256,
            "std_acc": 0.024477336456403907,
            "mean_erank": 10.480496667932869,
            "S": 0.873374722327739,
            "marginal": 0.011900000000000022
        },
        {
            "K": 16,
            "mean_acc": 0.9261500000000001,
            "std_acc": 0.02563791138138986,
            "mean_erank": 12.658942241506777,
            "S": 0.7911838900941736,
            "marginal": 0.0005500000000001615
        },
        {
            "K": 24,
            "mean_acc": 0.93585,
            "std_acc": 0.022392018667373417,
            "mean_erank": 14.793616863620406,
            "S": 0.6164007026508502,
            "marginal": 0.00969999999999982
        },
        {
            "K": 32,
            "mean_acc": 0.9393,
            "std_acc": 0.02440819534500656,
            "mean_erank": 17.38653322033304,
            "S": 0.5433291631354075,
            "marginal": 0.003450000000000064
        },
        {
            "K": 48,
            "mean_acc": 0.94005,
            "std_acc": 0.02395563608005431,
            "mean_erank": 20.414628533885804,
            "S": 0.4253047611226209,
            "marginal": 0.0007500000000000284
        },
        {
            "K": 64,
            "mean_acc": 0.9438,
            "std_acc": 0.014241137595009735,
            "mean_erank": 22.733834191647244,
            "S": 0.3552161592444882,
            "marginal": 0.00374999999999992
        },
        {
            "K": 128,
            "mean_acc": 0.9527500000000001,
            "std_acc": 0.01198175696632176,
            "mean_erank": 25.668069372619573,
            "S": 0.20053179197359042,
            "marginal": 0.008950000000000125
        },
        {
            "K": 256,
            "mean_acc": 0.964,
            "std_acc": 0.009746794344808976,
            "mean_erank": 28.7358236104409,
            "S": 0.11224931097828476,
            "marginal": 0.011249999999999871
        },
        {
            "K": 512,
            "mean_acc": 0.9678,
            "std_acc": 0.009690717207719976,
            "mean_erank": 31.288372617267527,
            "S": 0.06111010276810064,
            "marginal": 0.0038000000000000256
        },
        {
            "K": 1024,
            "mean_acc": 0.97835,
            "std_acc": 0.008071709856034228,
            "mean_erank": 33.45155947774651,
            "S": 0.03266753855248682,
            "marginal": 0.01055000000000006
        },
        {
            "K": 2048,
            "mean_acc": 0.9833999999999999,
            "std_acc": 0.006796322535018485,
            "mean_erank": 35.44252177869198,
            "S": 0.017305918837251945,
            "marginal": 0.005049999999999888
        },
        {
            "K": 4096,
            "mean_acc": 0.9854999999999999,
            "std_acc": 0.006745368781616031,
            "mean_erank": 36.82560214526214,
            "S": 0.00899062552374564,
            "marginal": 0.0020999999999999908
        }
    ],
    "MNIST_5v8": [
        {
            "K": 2,
            "mean_acc": 0.6598,
            "std_acc": 0.08777932558410323,
            "mean_erank": 1.7990461201735455,
            "S": 0.8995230600867727,
            "marginal": 0.0
        },
        {
            "K": 3,
            "mean_acc": 0.7158000000000001,
            "std_acc": 0.06977184245811485,
            "mean_erank": 3.1163522577451546,
            "S": 1.0387840859150514,
            "marginal": 0.05600000000000005
        },
        {
            "K": 4,
            "mean_acc": 0.74595,
            "std_acc": 0.06898530640650949,
            "mean_erank": 4.250194481005144,
            "S": 1.062548620251286,
            "marginal": 0.0301499999999999
        },
        {
            "K": 6,
            "mean_acc": 0.7952000000000001,
            "std_acc": 0.05675129954459193,
            "mean_erank": 6.561098113413227,
            "S": 1.0935163522355378,
            "marginal": 0.04925000000000013
        },
        {
            "K": 8,
            "mean_acc": 0.8281000000000001,
            "std_acc": 0.05375769712329575,
            "mean_erank": 7.810732901905128,
            "S": 0.976341612738141,
            "marginal": 0.03289999999999993
        },
        {
            "K": 12,
            "mean_acc": 0.8482999999999999,
            "std_acc": 0.0415645281460045,
            "mean_erank": 10.551221879252642,
            "S": 0.8792684899377202,
            "marginal": 0.020199999999999885
        },
        {
            "K": 16,
            "mean_acc": 0.8671499999999999,
            "std_acc": 0.031277028311526026,
            "mean_erank": 12.379143723543159,
            "S": 0.7736964827214474,
            "marginal": 0.018849999999999922
        },
        {
            "K": 24,
            "mean_acc": 0.8665499999999998,
            "std_acc": 0.0337449625870292,
            "mean_erank": 15.172879438140258,
            "S": 0.6322033099225107,
            "marginal": -0.0006000000000000449
        },
        {
            "K": 32,
            "mean_acc": 0.8815500000000001,
            "std_acc": 0.031100200963980924,
            "mean_erank": 16.468200337323655,
            "S": 0.5146312605413642,
            "marginal": 0.015000000000000235
        },
        {
            "K": 48,
            "mean_acc": 0.8832000000000001,
            "std_acc": 0.023817220660690027,
            "mean_erank": 18.82426071183033,
            "S": 0.39217209816313187,
            "marginal": 0.0016500000000000403
        },
        {
            "K": 64,
            "mean_acc": 0.8852499999999999,
            "std_acc": 0.025140853207478858,
            "mean_erank": 18.961324500451852,
            "S": 0.2962706953195602,
            "marginal": 0.0020499999999997742
        },
        {
            "K": 128,
            "mean_acc": 0.9003999999999999,
            "std_acc": 0.022468644818947135,
            "mean_erank": 24.2605667775788,
            "S": 0.18953567794983436,
            "marginal": 0.015149999999999997
        },
        {
            "K": 256,
            "mean_acc": 0.9118999999999999,
            "std_acc": 0.015219724044804496,
            "mean_erank": 26.54389132377711,
            "S": 0.10368707548350434,
            "marginal": 0.011500000000000066
        },
        {
            "K": 512,
            "mean_acc": 0.9389500000000003,
            "std_acc": 0.01086381608828131,
            "mean_erank": 29.228714999838648,
            "S": 0.05708733398405986,
            "marginal": 0.02705000000000035
        },
        {
            "K": 1024,
            "mean_acc": 0.9442499999999998,
            "std_acc": 0.01075,
            "mean_erank": 31.871859639202896,
            "S": 0.031124862928909078,
            "marginal": 0.005299999999999527
        },
        {
            "K": 2048,
            "mean_acc": 0.9501000000000002,
            "std_acc": 0.00880284045067273,
            "mean_erank": 34.20641420440512,
            "S": 0.016702350685744688,
            "marginal": 0.005850000000000355
        },
        {
            "K": 4096,
            "mean_acc": 0.94785,
            "std_acc": 0.008958375968890786,
            "mean_erank": 36.21434494743622,
            "S": 0.00884139280943267,
            "marginal": -0.0022500000000001963
        }
    ],
    "Fashion_0v1": [
        {
            "K": 2,
            "mean_acc": 0.8523000000000001,
            "std_acc": 0.07995755123814134,
            "mean_erank": 1.6748002064145333,
            "S": 0.8374001032072667,
            "marginal": 0.0
        },
        {
            "K": 3,
            "mean_acc": 0.8835,
            "std_acc": 0.06904708538381615,
            "mean_erank": 2.783147725356593,
            "S": 0.9277159084521976,
            "marginal": 0.031199999999999894
        },
        {
            "K": 4,
            "mean_acc": 0.90765,
            "std_acc": 0.06307220069095416,
            "mean_erank": 3.5632137894334392,
            "S": 0.8908034473583598,
            "marginal": 0.024150000000000005
        },
        {
            "K": 6,
            "mean_acc": 0.91775,
            "std_acc": 0.039988279532883135,
            "mean_erank": 4.8389550858360035,
            "S": 0.8064925143060006,
            "marginal": 0.010099999999999998
        },
        {
            "K": 8,
            "mean_acc": 0.93045,
            "std_acc": 0.03437546363323699,
            "mean_erank": 5.543940064459365,
            "S": 0.6929925080574206,
            "marginal": 0.012700000000000045
        },
        {
            "K": 12,
            "mean_acc": 0.9499500000000001,
            "std_acc": 0.02364048434360006,
            "mean_erank": 6.92668513512794,
            "S": 0.5772237612606617,
            "marginal": 0.019500000000000073
        },
        {
            "K": 16,
            "mean_acc": 0.9451999999999999,
            "std_acc": 0.01707219962395004,
            "mean_erank": 7.841215854586072,
            "S": 0.4900759909116295,
            "marginal": -0.004750000000000143
        },
        {
            "K": 24,
            "mean_acc": 0.9614499999999999,
            "std_acc": 0.016109702045661804,
            "mean_erank": 8.744226106439477,
            "S": 0.3643427544349782,
            "marginal": 0.016249999999999987
        },
        {
            "K": 32,
            "mean_acc": 0.96065,
            "std_acc": 0.01639214751031725,
            "mean_erank": 9.561300398828696,
            "S": 0.29879063746339674,
            "marginal": -0.0007999999999999119
        },
        {
            "K": 48,
            "mean_acc": 0.9616500000000001,
            "std_acc": 0.014479381892884792,
            "mean_erank": 11.047340893383236,
            "S": 0.23015293527881742,
            "marginal": 0.001000000000000112
        },
        {
            "K": 64,
            "mean_acc": 0.96435,
            "std_acc": 0.011956274503372704,
            "mean_erank": 11.993234362706982,
            "S": 0.1873942869172966,
            "marginal": 0.0026999999999999247
        },
        {
            "K": 128,
            "mean_acc": 0.9722,
            "std_acc": 0.01149608629055994,
            "mean_erank": 13.755334645176113,
            "S": 0.10746355191543838,
            "marginal": 0.007849999999999913
        },
        {
            "K": 256,
            "mean_acc": 0.97515,
            "std_acc": 0.009815930928852348,
            "mean_erank": 16.092084354639013,
            "S": 0.06285970451030864,
            "marginal": 0.002950000000000008
        },
        {
            "K": 512,
            "mean_acc": 0.9722,
            "std_acc": 0.010984534582766815,
            "mean_erank": 17.90565436259528,
            "S": 0.0349719811769439,
            "marginal": -0.002950000000000008
        },
        {
            "K": 1024,
            "mean_acc": 0.9775999999999999,
            "std_acc": 0.007793587107359493,
            "mean_erank": 19.134604355095945,
            "S": 0.018686137065523384,
            "marginal": 0.00539999999999996
        },
        {
            "K": 2048,
            "mean_acc": 0.9840000000000001,
            "std_acc": 0.006363961030678931,
            "mean_erank": 20.24393900348399,
            "S": 0.009884735841544917,
            "marginal": 0.006400000000000183
        },
        {
            "K": 4096,
            "mean_acc": 0.98555,
            "std_acc": 0.005685288031401758,
            "mean_erank": 20.682779870278317,
            "S": 0.005049506804267167,
            "marginal": 0.0015499999999999403
        }
    ],
    "Fashion_2v6": [
        {
            "K": 2,
            "mean_acc": 0.5548,
            "std_acc": 0.06297785325017041,
            "mean_erank": 1.7130015644255798,
            "S": 0.8565007822127899,
            "marginal": 0.0
        },
        {
            "K": 3,
            "mean_acc": 0.5674999999999999,
            "std_acc": 0.08707468059085832,
            "mean_erank": 2.697391118151649,
            "S": 0.8991303727172163,
            "marginal": 0.012699999999999934
        },
        {
            "K": 4,
            "mean_acc": 0.6161999999999999,
            "std_acc": 0.08415051990332562,
            "mean_erank": 3.4999774827759222,
            "S": 0.8749943706939806,
            "marginal": 0.048699999999999966
        },
        {
            "K": 6,
            "mean_acc": 0.65925,
            "std_acc": 0.05684243573247015,
            "mean_erank": 4.520479415236422,
            "S": 0.753413235872737,
            "marginal": 0.043050000000000144
        },
        {
            "K": 8,
            "mean_acc": 0.66535,
            "std_acc": 0.05505454113876528,
            "mean_erank": 5.290386239859384,
            "S": 0.661298279982423,
            "marginal": 0.006099999999999994
        },
        {
            "K": 12,
            "mean_acc": 0.69835,
            "std_acc": 0.05021107945463829,
            "mean_erank": 6.494925219510004,
            "S": 0.5412437682925003,
            "marginal": 0.03300000000000003
        },
        {
            "K": 16,
            "mean_acc": 0.7071999999999999,
            "std_acc": 0.04765668893240485,
            "mean_erank": 7.458173441053382,
            "S": 0.46613584006583636,
            "marginal": 0.008849999999999913
        },
        {
            "K": 24,
            "mean_acc": 0.7293499999999998,
            "std_acc": 0.03996814356459405,
            "mean_erank": 8.090255421386708,
            "S": 0.33709397589111284,
            "marginal": 0.022149999999999892
        },
        {
            "K": 32,
            "mean_acc": 0.7293000000000001,
            "std_acc": 0.03729959785306002,
            "mean_erank": 8.736077402825874,
            "S": 0.27300241883830856,
            "marginal": -4.999999999977245e-05
        },
        {
            "K": 48,
            "mean_acc": 0.7397,
            "std_acc": 0.03900525605607532,
            "mean_erank": 9.765984047194785,
            "S": 0.20345800098322467,
            "marginal": 0.010399999999999965
        },
        {
            "K": 64,
            "mean_acc": 0.7334499999999999,
            "std_acc": 0.04018672044344997,
            "mean_erank": 10.579392507850265,
            "S": 0.1653030079351604,
            "marginal": -0.006250000000000089
        },
        {
            "K": 128,
            "mean_acc": 0.7790499999999999,
            "std_acc": 0.02140029205408189,
            "mean_erank": 11.629035255890962,
            "S": 0.09085183793664814,
            "marginal": 0.045599999999999974
        },
        {
            "K": 256,
            "mean_acc": 0.8132,
            "std_acc": 0.01690443728729234,
            "mean_erank": 12.725191992717571,
            "S": 0.04970778122155301,
            "marginal": 0.034150000000000125
        },
        {
            "K": 512,
            "mean_acc": 0.8231999999999999,
            "std_acc": 0.01721220497205399,
            "mean_erank": 13.38008338222372,
            "S": 0.026132975355905703,
            "marginal": 0.009999999999999898
        },
        {
            "K": 1024,
            "mean_acc": 0.82795,
            "std_acc": 0.016708455943024777,
            "mean_erank": 13.924243910671747,
            "S": 0.013597894444015378,
            "marginal": 0.004750000000000032
        },
        {
            "K": 2048,
            "mean_acc": 0.8268,
            "std_acc": 0.019339338147930502,
            "mean_erank": 14.26489825880692,
            "S": 0.006965282352933066,
            "marginal": -0.0011499999999999844
        },
        {
            "K": 4096,
            "mean_acc": 0.835,
            "std_acc": 0.018601075237738268,
            "mean_erank": 14.45877838721497,
            "S": 0.003529975192191155,
            "marginal": 0.008199999999999985
        }
    ],
    "Fashion_3v5": [
        {
            "K": 2,
            "mean_acc": 0.9522000000000002,
            "std_acc": 0.05500599967276297,
            "mean_erank": 1.7833252060448868,
            "S": 0.8916626030224434,
            "marginal": 0.0
        },
        {
            "K": 3,
            "mean_acc": 0.96465,
            "std_acc": 0.03317005426585855,
            "mean_erank": 3.0812031410055023,
            "S": 1.0270677136685007,
            "marginal": 0.01244999999999985
        },
        {
            "K": 4,
            "mean_acc": 0.9657500000000002,
            "std_acc": 0.026477584859650634,
            "mean_erank": 4.185174221000047,
            "S": 1.0462935552500117,
            "marginal": 0.001100000000000212
        },
        {
            "K": 6,
            "mean_acc": 0.97885,
            "std_acc": 0.01860248639295297,
            "mean_erank": 5.901141988030422,
            "S": 0.983523664671737,
            "marginal": 0.013099999999999778
        },
        {
            "K": 8,
            "mean_acc": 0.9860000000000001,
            "std_acc": 0.011968709203585833,
            "mean_erank": 7.785787876734454,
            "S": 0.9732234845918067,
            "marginal": 0.007150000000000101
        },
        {
            "K": 12,
            "mean_acc": 0.9902500000000001,
            "std_acc": 0.006269968101992234,
            "mean_erank": 9.837374692356327,
            "S": 0.8197812243630272,
            "marginal": 0.004249999999999976
        },
        {
            "K": 16,
            "mean_acc": 0.99025,
            "std_acc": 0.008518362518700421,
            "mean_erank": 10.979667823262083,
            "S": 0.6862292389538802,
            "marginal": -1.1102230246251565e-16
        },
        {
            "K": 24,
            "mean_acc": 0.9928,
            "std_acc": 0.005801723881744118,
            "mean_erank": 13.652811739216956,
            "S": 0.5688671558007065,
            "marginal": 0.0025500000000000522
        },
        {
            "K": 32,
            "mean_acc": 0.9921500000000002,
            "std_acc": 0.005744780239486977,
            "mean_erank": 14.946932984995879,
            "S": 0.4670916557811212,
            "marginal": -0.0006499999999998174
        },
        {
            "K": 48,
            "mean_acc": 0.9938000000000001,
            "std_acc": 0.005005996404313525,
            "mean_erank": 16.847962864963474,
            "S": 0.3509992263534057,
            "marginal": 0.0016499999999999293
        },
        {
            "K": 64,
            "mean_acc": 0.9956499999999999,
            "std_acc": 0.0034572387826125126,
            "mean_erank": 18.44726959665967,
            "S": 0.28823858744780734,
            "marginal": 0.0018499999999997963
        },
        {
            "K": 128,
            "mean_acc": 0.9966000000000002,
            "std_acc": 0.0022226110770892865,
            "mean_erank": 20.182666280645012,
            "S": 0.15767708031753916,
            "marginal": 0.0009500000000002284
        },
        {
            "K": 256,
            "mean_acc": 0.99645,
            "std_acc": 0.0030037476591751157,
            "mean_erank": 22.053488734310232,
            "S": 0.08614644036839934,
            "marginal": -0.00015000000000020552
        },
        {
            "K": 512,
            "mean_acc": 0.9977000000000001,
            "std_acc": 0.0021702534414210673,
            "mean_erank": 23.375526499078575,
            "S": 0.04565532519351284,
            "marginal": 0.0012500000000001954
        },
        {
            "K": 1024,
            "mean_acc": 0.99775,
            "std_acc": 0.002249999999999992,
            "mean_erank": 24.742951446661014,
            "S": 0.024163038522129896,
            "marginal": 4.999999999988347e-05
        },
        {
            "K": 2048,
            "mean_acc": 0.9979500000000001,
            "std_acc": 0.0023286262044389964,
            "mean_erank": 26.11364739875668,
            "S": 0.01275080439392416,
            "marginal": 0.000200000000000089
        },
        {
            "K": 4096,
            "mean_acc": 0.9982000000000002,
            "std_acc": 0.002238302928559927,
            "mean_erank": 27.355891445180657,
            "S": 0.006678684434858559,
            "marginal": 0.0002500000000000835
        }
    ],
    "Fashion_4v6": [
        {
            "K": 2,
            "mean_acc": 0.57945,
            "std_acc": 0.09675005167957276,
            "mean_erank": 1.7177521575486399,
            "S": 0.8588760787743199,
            "marginal": 0.0
        },
        {
            "K": 3,
            "mean_acc": 0.61535,
            "std_acc": 0.07822565116379666,
            "mean_erank": 2.7282509497339515,
            "S": 0.9094169832446505,
            "marginal": 0.03589999999999993
        },
        {
            "K": 4,
            "mean_acc": 0.6406000000000001,
            "std_acc": 0.06695065346955174,
            "mean_erank": 3.584102346175979,
            "S": 0.8960255865439948,
            "marginal": 0.025250000000000106
        },
        {
            "K": 6,
            "mean_acc": 0.6766,
            "std_acc": 0.058248948488363296,
            "mean_erank": 4.498169476772086,
            "S": 0.7496949127953476,
            "marginal": 0.03599999999999992
        },
        {
            "K": 8,
            "mean_acc": 0.6908,
            "std_acc": 0.05568312132055817,
            "mean_erank": 5.578695514268069,
            "S": 0.6973369392835086,
            "marginal": 0.01419999999999999
        },
        {
            "K": 12,
            "mean_acc": 0.7139,
            "std_acc": 0.05324978873197528,
            "mean_erank": 6.626471170383525,
            "S": 0.5522059308652937,
            "marginal": 0.02310000000000001
        },
        {
            "K": 16,
            "mean_acc": 0.7411999999999999,
            "std_acc": 0.04157896102598043,
            "mean_erank": 7.526067317188026,
            "S": 0.47037920732425165,
            "marginal": 0.02729999999999988
        },
        {
            "K": 24,
            "mean_acc": 0.7625,
            "std_acc": 0.03523137805990564,
            "mean_erank": 8.518780100408458,
            "S": 0.35494917085035244,
            "marginal": 0.021300000000000097
        },
        {
            "K": 32,
            "mean_acc": 0.7674,
            "std_acc": 0.03128881589322293,
            "mean_erank": 9.299681696812495,
            "S": 0.2906150530253905,
            "marginal": 0.0049000000000000155
        },
        {
            "K": 48,
            "mean_acc": 0.76685,
            "std_acc": 0.03772204262762025,
            "mean_erank": 10.387928415344835,
            "S": 0.21641517531968404,
            "marginal": -0.0005499999999999394
        },
        {
            "K": 64,
            "mean_acc": 0.75825,
            "std_acc": 0.03955455093917765,
            "mean_erank": 11.472474024617483,
            "S": 0.17925740663464818,
            "marginal": -0.008600000000000052
        },
        {
            "K": 128,
            "mean_acc": 0.79525,
            "std_acc": 0.023586277790274578,
            "mean_erank": 12.366155982617643,
            "S": 0.09661059361420034,
            "marginal": 0.03700000000000003
        },
        {
            "K": 256,
            "mean_acc": 0.8305500000000001,
            "std_acc": 0.020051745559925702,
            "mean_erank": 13.582900007280392,
            "S": 0.05305820315343903,
            "marginal": 0.03530000000000011
        },
        {
            "K": 512,
            "mean_acc": 0.8470000000000002,
            "std_acc": 0.01706604816587602,
            "mean_erank": 14.419038831161952,
            "S": 0.028162185217113188,
            "marginal": 0.016450000000000076
        },
        {
            "K": 1024,
            "mean_acc": 0.8530500000000001,
            "std_acc": 0.017279250562452067,
            "mean_erank": 14.991986010084336,
            "S": 0.014640611337972984,
            "marginal": 0.006049999999999889
        },
        {
            "K": 2048,
            "mean_acc": 0.8564,
            "std_acc": 0.014266744548074032,
            "mean_erank": 15.50566228570136,
            "S": 0.007571124162940117,
            "marginal": 0.003349999999999964
        },
        {
            "K": 4096,
            "mean_acc": 0.85685,
            "std_acc": 0.01671683283400298,
            "mean_erank": 15.704448467588707,
            "S": 0.003834093864157399,
            "marginal": 0.00044999999999995044
        }
    ],
    "Fashion_5v7": [
        {
            "K": 2,
            "mean_acc": 0.7160500000000001,
            "std_acc": 0.09216166502402177,
            "mean_erank": 1.7289558878014426,
            "S": 0.8644779439007213,
            "marginal": 0.0
        },
        {
            "K": 3,
            "mean_acc": 0.7342500000000001,
            "std_acc": 0.06912353072579554,
            "mean_erank": 2.7925763157926924,
            "S": 0.9308587719308975,
            "marginal": 0.018199999999999994
        },
        {
            "K": 4,
            "mean_acc": 0.7598999999999999,
            "std_acc": 0.08029315039279503,
            "mean_erank": 3.6669244367319545,
            "S": 0.9167311091829886,
            "marginal": 0.02564999999999984
        },
        {
            "K": 6,
            "mean_acc": 0.7934,
            "std_acc": 0.058077017829774966,
            "mean_erank": 4.828146975568107,
            "S": 0.8046911625946844,
            "marginal": 0.033500000000000085
        },
        {
            "K": 8,
            "mean_acc": 0.8042500000000001,
            "std_acc": 0.04335680454092529,
            "mean_erank": 5.849480532121041,
            "S": 0.7311850665151302,
            "marginal": 0.010850000000000137
        },
        {
            "K": 12,
            "mean_acc": 0.81985,
            "std_acc": 0.04698779096744174,
            "mean_erank": 7.781375020033938,
            "S": 0.6484479183361614,
            "marginal": 0.015599999999999836
        },
        {
            "K": 16,
            "mean_acc": 0.8257499999999999,
            "std_acc": 0.03947546706500127,
            "mean_erank": 8.601909845342051,
            "S": 0.5376193653338782,
            "marginal": 0.005899999999999905
        },
        {
            "K": 24,
            "mean_acc": 0.8533,
            "std_acc": 0.032624530647964875,
            "mean_erank": 10.596023591050882,
            "S": 0.4415009829604534,
            "marginal": 0.027550000000000074
        },
        {
            "K": 32,
            "mean_acc": 0.8481999999999998,
            "std_acc": 0.027708482455739075,
            "mean_erank": 11.270246659491136,
            "S": 0.352195208109098,
            "marginal": -0.0051000000000001044
        },
        {
            "K": 48,
            "mean_acc": 0.8647500000000001,
            "std_acc": 0.028645462118806884,
            "mean_erank": 13.598746854167427,
            "S": 0.2833072261284881,
            "marginal": 0.016550000000000287
        },
        {
            "K": 64,
            "mean_acc": 0.8665999999999999,
            "std_acc": 0.02805690645812542,
            "mean_erank": 14.369740571043664,
            "S": 0.22452719642255725,
            "marginal": 0.0018499999999997963
        },
        {
            "K": 128,
            "mean_acc": 0.88165,
            "std_acc": 0.019733284065253806,
            "mean_erank": 16.676421891913254,
            "S": 0.1302845460305723,
            "marginal": 0.015050000000000119
        },
        {
            "K": 256,
            "mean_acc": 0.9091,
            "std_acc": 0.017872884490199123,
            "mean_erank": 18.303913019463984,
            "S": 0.07149966023228119,
            "marginal": 0.027449999999999974
        },
        {
            "K": 512,
            "mean_acc": 0.9273999999999998,
            "std_acc": 0.01373826772195097,
            "mean_erank": 20.4449221271114,
            "S": 0.039931488529514454,
            "marginal": 0.01829999999999976
        },
        {
            "K": 1024,
            "mean_acc": 0.9384999999999999,
            "std_acc": 0.011779218989389731,
            "mean_erank": 22.463443772818685,
            "S": 0.021936956809393247,
            "marginal": 0.01110000000000011
        },
        {
            "K": 2048,
            "mean_acc": 0.94225,
            "std_acc": 0.010703387314303812,
            "mean_erank": 24.04144799583993,
            "S": 0.011738988279218716,
            "marginal": 0.003750000000000142
        },
        {
            "K": 4096,
            "mean_acc": 0.9444,
            "std_acc": 0.012263360061581813,
            "mean_erank": 26.10392100174423,
            "S": 0.006373027588316462,
            "marginal": 0.0021499999999999853
        }
    ],
    "Kuzushiji_0v1": [
        {
            "K": 2,
            "mean_acc": 0.8661999999999999,
            "std_acc": 0.10798407289966423,
            "mean_erank": 1.8211868228164483,
            "S": 0.9105934114082241,
            "marginal": 0.0
        },
        {
            "K": 3,
            "mean_acc": 0.9079500000000001,
            "std_acc": 0.059855429995949394,
            "mean_erank": 3.3637440983465,
            "S": 1.1212480327821666,
            "marginal": 0.04175000000000029
        },
        {
            "K": 4,
            "mean_acc": 0.9247,
            "std_acc": 0.03409413439288348,
            "mean_erank": 4.764041925916986,
            "S": 1.1910104814792466,
            "marginal": 0.01674999999999982
        },
        {
            "K": 6,
            "mean_acc": 0.9383499999999999,
            "std_acc": 0.023593484270026756,
            "mean_erank": 7.297226225233673,
            "S": 1.2162043708722787,
            "marginal": 0.01364999999999994
        },
        {
            "K": 8,
            "mean_acc": 0.9403999999999999,
            "std_acc": 0.020459472133953008,
            "mean_erank": 9.655341049874252,
            "S": 1.2069176312342815,
            "marginal": 0.0020499999999999963
        },
        {
            "K": 12,
            "mean_acc": 0.9545,
            "std_acc": 0.020000000000000007,
            "mean_erank": 13.640629840564635,
            "S": 1.1367191533803862,
            "marginal": 0.014100000000000112
        },
        {
            "K": 16,
            "mean_acc": 0.9527999999999999,
            "std_acc": 0.019922600231897444,
            "mean_erank": 16.474045296412907,
            "S": 1.0296278310258067,
            "marginal": -0.0017000000000001458
        },
        {
            "K": 24,
            "mean_acc": 0.9593499999999999,
            "std_acc": 0.019841937909387784,
            "mean_erank": 20.32931375894514,
            "S": 0.8470547399560475,
            "marginal": 0.006550000000000056
        },
        {
            "K": 32,
            "mean_acc": 0.9624999999999999,
            "std_acc": 0.017277152543171005,
            "mean_erank": 23.598335575498105,
            "S": 0.7374479867343158,
            "marginal": 0.003149999999999986
        },
        {
            "K": 48,
            "mean_acc": 0.9648,
            "std_acc": 0.011367057666784332,
            "mean_erank": 27.628165563781035,
            "S": 0.5755867825787716,
            "marginal": 0.0023000000000000798
        },
        {
            "K": 64,
            "mean_acc": 0.9660000000000001,
            "std_acc": 0.013313526955694351,
            "mean_erank": 29.550855433944026,
            "S": 0.4617321161553754,
            "marginal": 0.0012000000000000899
        },
        {
            "K": 128,
            "mean_acc": 0.9679000000000001,
            "std_acc": 0.011665761869676591,
            "mean_erank": 33.003557100419926,
            "S": 0.25784028984703067,
            "marginal": 0.0019000000000000128
        },
        {
            "K": 256,
            "mean_acc": 0.971,
            "std_acc": 0.009733961166965899,
            "mean_erank": 35.10833191634921,
            "S": 0.1371419215482391,
            "marginal": 0.0030999999999998806
        },
        {
            "K": 512,
            "mean_acc": 0.9721000000000001,
            "std_acc": 0.008865100112237886,
            "mean_erank": 36.06773313650148,
            "S": 0.07044479128222945,
            "marginal": 0.001100000000000101
        },
        {
            "K": 1024,
            "mean_acc": 0.98135,
            "std_acc": 0.006465485287277369,
            "mean_erank": 36.78021171598015,
            "S": 0.035918175503886866,
            "marginal": 0.00924999999999987
        },
        {
            "K": 2048,
            "mean_acc": 0.986,
            "std_acc": 0.005873670062235372,
            "mean_erank": 37.03924353722347,
            "S": 0.018085568133409897,
            "marginal": 0.004650000000000043
        },
        {
            "K": 4096,
            "mean_acc": 0.9871000000000001,
            "std_acc": 0.005817215828899596,
            "mean_erank": 37.17533936543261,
            "S": 0.009076010587263822,
            "marginal": 0.001100000000000101
        }
    ],
    "USPS_1v2": [
        {
            "K": 2,
            "mean_acc": 0.9366,
            "std_acc": 0.07131928210519227,
            "mean_erank": 1.3920855772881966,
            "S": 0.6960427886440983,
            "marginal": 0.0
        },
        {
            "K": 3,
            "mean_acc": 0.9592999999999999,
            "std_acc": 0.03876867292028448,
            "mean_erank": 2.372344952202263,
            "S": 0.7907816507340876,
            "marginal": 0.022699999999999942
        },
        {
            "K": 4,
            "mean_acc": 0.9733000000000002,
            "std_acc": 0.03133065591397665,
            "mean_erank": 3.0625824505341384,
            "S": 0.7656456126335346,
            "marginal": 0.014000000000000234
        },
        {
            "K": 6,
            "mean_acc": 0.9818000000000001,
            "std_acc": 0.02016829194552678,
            "mean_erank": 4.257094582891878,
            "S": 0.709515763815313,
            "marginal": 0.008499999999999952
        },
        {
            "K": 8,
            "mean_acc": 0.9860000000000001,
            "std_acc": 0.022561028345356962,
            "mean_erank": 5.268984439495585,
            "S": 0.6586230549369482,
            "marginal": 0.0041999999999999815
        },
        {
            "K": 12,
            "mean_acc": 0.9930999999999999,
            "std_acc": 0.00859592926913665,
            "mean_erank": 6.635554170048874,
            "S": 0.5529628475040728,
            "marginal": 0.007099999999999773
        },
        {
            "K": 16,
            "mean_acc": 0.9945,
            "std_acc": 0.006726812023536861,
            "mean_erank": 7.609910142929741,
            "S": 0.4756193839331088,
            "marginal": 0.0014000000000001789
        },
        {
            "K": 24,
            "mean_acc": 0.9949999999999999,
            "std_acc": 0.005656854249492385,
            "mean_erank": 9.11741747527242,
            "S": 0.3798923948030175,
            "marginal": 0.0004999999999998339
        },
        {
            "K": 32,
            "mean_acc": 0.997,
            "std_acc": 0.0037416573867739447,
            "mean_erank": 9.98648395068613,
            "S": 0.3120776234589416,
            "marginal": 0.002000000000000113
        },
        {
            "K": 48,
            "mean_acc": 0.9973000000000001,
            "std_acc": 0.003634556369077253,
            "mean_erank": 11.347817696404148,
            "S": 0.2364128686750864,
            "marginal": 0.000300000000000078
        },
        {
            "K": 64,
            "mean_acc": 0.9969,
            "std_acc": 0.004109744517606907,
            "mean_erank": 11.744555954617194,
            "S": 0.18350868679089366,
            "marginal": -0.00040000000000006697
        },
        {
            "K": 128,
            "mean_acc": 0.9972,
            "std_acc": 0.0036276714294434143,
            "mean_erank": 13.483526837122746,
            "S": 0.10534005341502145,
            "marginal": 0.00029999999999996696
        },
        {
            "K": 256,
            "mean_acc": 0.9973000000000001,
            "std_acc": 0.003634556369077253,
            "mean_erank": 14.23535476705157,
            "S": 0.055606854558795195,
            "marginal": 0.00010000000000010001
        },
        {
            "K": 512,
            "mean_acc": 0.9973000000000001,
            "std_acc": 0.003769615364994156,
            "mean_erank": 15.08075583988249,
            "S": 0.02945460124977049,
            "marginal": 0.0
        }
    ],
    "BreastCancer": [
        {
            "K": 2,
            "mean_acc": 0.8380999999999998,
            "std_acc": 0.07835425961618168,
            "mean_erank": 1.685403217527779,
            "S": 0.8427016087638896,
            "marginal": 0.0
        },
        {
            "K": 3,
            "mean_acc": 0.8543000000000002,
            "std_acc": 0.07596387299236396,
            "mean_erank": 2.724286678491507,
            "S": 0.908095559497169,
            "marginal": 0.016200000000000325
        },
        {
            "K": 4,
            "mean_acc": 0.8807,
            "std_acc": 0.0629325829757527,
            "mean_erank": 3.4141899374878744,
            "S": 0.8535474843719686,
            "marginal": 0.026399999999999868
        },
        {
            "K": 6,
            "mean_acc": 0.8804000000000001,
            "std_acc": 0.06080986762031306,
            "mean_erank": 4.366018892002037,
            "S": 0.7276698153336728,
            "marginal": -0.00029999999999996696
        },
        {
            "K": 8,
            "mean_acc": 0.9097,
            "std_acc": 0.04546328188769482,
            "mean_erank": 5.0293836320758105,
            "S": 0.6286729540094763,
            "marginal": 0.02929999999999988
        },
        {
            "K": 12,
            "mean_acc": 0.9098,
            "std_acc": 0.04303440484077826,
            "mean_erank": 5.900582260323173,
            "S": 0.4917151883602644,
            "marginal": 0.00010000000000010001
        },
        {
            "K": 16,
            "mean_acc": 0.9197,
            "std_acc": 0.03861230373857534,
            "mean_erank": 6.439145974973107,
            "S": 0.40244662343581916,
            "marginal": 0.009899999999999909
        },
        {
            "K": 24,
            "mean_acc": 0.9393,
            "std_acc": 0.026009805843181508,
            "mean_erank": 6.858090095266133,
            "S": 0.2857537539694222,
            "marginal": 0.019600000000000062
        },
        {
            "K": 32,
            "mean_acc": 0.9369999999999998,
            "std_acc": 0.030643106892089107,
            "mean_erank": 7.2071499954204565,
            "S": 0.22522343735688927,
            "marginal": -0.0023000000000001908
        },
        {
            "K": 48,
            "mean_acc": 0.945,
            "std_acc": 0.024351591323771817,
            "mean_erank": 7.641086132834594,
            "S": 0.15918929443405402,
            "marginal": 0.008000000000000118
        },
        {
            "K": 64,
            "mean_acc": 0.9449,
            "std_acc": 0.02251643843950457,
            "mean_erank": 7.911837430592904,
            "S": 0.12362245985301412,
            "marginal": -9.999999999998899e-05
        },
        {
            "K": 100,
            "mean_acc": 0.9424999999999999,
            "std_acc": 0.021183720164314832,
            "mean_erank": 8.20400754461391,
            "S": 0.0820400754461391,
            "marginal": -0.0024000000000000687
        }
    ],
    "CIFAR_0v1": [
        {
            "K": 2,
            "mean_acc": 0.61375,
            "std_acc": 0.09032476127840029,
            "mean_erank": 1.8188679828316532,
            "S": 0.9094339914158266,
            "marginal": 0.0
        },
        {
            "K": 3,
            "mean_acc": 0.60945,
            "std_acc": 0.0862442606786098,
            "mean_erank": 3.1853171934401643,
            "S": 1.0617723978133882,
            "marginal": -0.0042999999999999705
        },
        {
            "K": 4,
            "mean_acc": 0.622,
            "std_acc": 0.05882813952523061,
            "mean_erank": 4.238022896291451,
            "S": 1.0595057240728627,
            "marginal": 0.01254999999999995
        },
        {
            "K": 6,
            "mean_acc": 0.6518999999999999,
            "std_acc": 0.05381347414913853,
            "mean_erank": 6.166493505801992,
            "S": 1.0277489176336654,
            "marginal": 0.029899999999999927
        },
        {
            "K": 8,
            "mean_acc": 0.6502,
            "std_acc": 0.05435034498510567,
            "mean_erank": 7.311228810380116,
            "S": 0.9139036012975145,
            "marginal": -0.0016999999999999238
        },
        {
            "K": 12,
            "mean_acc": 0.6853500000000001,
            "std_acc": 0.03988423874163828,
            "mean_erank": 8.836306281044529,
            "S": 0.7363588567537107,
            "marginal": 0.035150000000000126
        },
        {
            "K": 16,
            "mean_acc": 0.6838000000000001,
            "std_acc": 0.04669378973696609,
            "mean_erank": 9.999724546717676,
            "S": 0.6249827841698548,
            "marginal": -0.0015500000000000513
        },
        {
            "K": 24,
            "mean_acc": 0.6957000000000001,
            "std_acc": 0.03526343715521786,
            "mean_erank": 11.579859111343582,
            "S": 0.4824941296393159,
            "marginal": 0.011900000000000022
        },
        {
            "K": 32,
            "mean_acc": 0.7056500000000001,
            "std_acc": 0.03817332183606767,
            "mean_erank": 12.435806166716098,
            "S": 0.38861894270987807,
            "marginal": 0.009950000000000014
        },
        {
            "K": 48,
            "mean_acc": 0.6923999999999999,
            "std_acc": 0.04227280449650816,
            "mean_erank": 13.206535813828753,
            "S": 0.275136162788099,
            "marginal": -0.013250000000000206
        },
        {
            "K": 64,
            "mean_acc": 0.6942500000000001,
            "std_acc": 0.038859522642461786,
            "mean_erank": 13.748969235864566,
            "S": 0.21482764431038384,
            "marginal": 0.0018500000000002403
        },
        {
            "K": 128,
            "mean_acc": 0.74185,
            "std_acc": 0.027380695754490984,
            "mean_erank": 14.533291381009981,
            "S": 0.11354133891414048,
            "marginal": 0.047599999999999865
        },
        {
            "K": 256,
            "mean_acc": 0.7792999999999999,
            "std_acc": 0.02086887634732642,
            "mean_erank": 14.863331597230523,
            "S": 0.05805988905168173,
            "marginal": 0.03744999999999987
        },
        {
            "K": 512,
            "mean_acc": 0.79205,
            "std_acc": 0.017816354846039644,
            "mean_erank": 15.34981632425012,
            "S": 0.029980110008301017,
            "marginal": 0.01275000000000015
        },
        {
            "K": 1024,
            "mean_acc": 0.8005000000000001,
            "std_acc": 0.017036725037400807,
            "mean_erank": 15.385499001877406,
            "S": 0.015024901369020904,
            "marginal": 0.008450000000000069
        },
        {
            "K": 2048,
            "mean_acc": 0.7985999999999999,
            "std_acc": 0.013956718812099063,
            "mean_erank": 15.348235813930225,
            "S": 0.007494255768520618,
            "marginal": -0.0019000000000002348
        },
        {
            "K": 4096,
            "mean_acc": 0.8076000000000001,
            "std_acc": 0.017392239648762884,
            "mean_erank": 15.403630471860563,
            "S": 0.0037606519706690827,
            "marginal": 0.00900000000000023
        }
    ],
    "CIFAR_3v5": [
        {
            "K": 2,
            "mean_acc": 0.505,
            "std_acc": 0.032927951652053915,
            "mean_erank": 1.819294847950421,
            "S": 0.9096474239752105,
            "marginal": 0.0
        },
        {
            "K": 3,
            "mean_acc": 0.51525,
            "std_acc": 0.04139519899698514,
            "mean_erank": 3.2144056144164983,
            "S": 1.0714685381388327,
            "marginal": 0.010249999999999981
        },
        {
            "K": 4,
            "mean_acc": 0.50655,
            "std_acc": 0.03336873536710674,
            "mean_erank": 4.221845476809945,
            "S": 1.0554613692024863,
            "marginal": -0.008700000000000041
        },
        {
            "K": 6,
            "mean_acc": 0.51365,
            "std_acc": 0.034297266654939144,
            "mean_erank": 6.065306593619733,
            "S": 1.0108844322699555,
            "marginal": 0.007100000000000106
        },
        {
            "K": 8,
            "mean_acc": 0.5169,
            "std_acc": 0.03626141199677696,
            "mean_erank": 7.759747945752522,
            "S": 0.9699684932190652,
            "marginal": 0.003249999999999975
        },
        {
            "K": 12,
            "mean_acc": 0.5218499999999999,
            "std_acc": 0.031176152745327645,
            "mean_erank": 9.68402695595253,
            "S": 0.8070022463293776,
            "marginal": 0.004949999999999899
        },
        {
            "K": 16,
            "mean_acc": 0.51415,
            "std_acc": 0.027702030611491284,
            "mean_erank": 10.652174984073048,
            "S": 0.6657609365045655,
            "marginal": -0.007699999999999929
        },
        {
            "K": 24,
            "mean_acc": 0.5148499999999999,
            "std_acc": 0.027246146516525977,
            "mean_erank": 12.793598268858561,
            "S": 0.5330665945357734,
            "marginal": 0.0006999999999999229
        },
        {
            "K": 32,
            "mean_acc": 0.5199999999999999,
            "std_acc": 0.03214031735997639,
            "mean_erank": 13.735047479265809,
            "S": 0.42922023372705653,
            "marginal": 0.005149999999999988
        },
        {
            "K": 48,
            "mean_acc": 0.52345,
            "std_acc": 0.030302186389764025,
            "mean_erank": 14.732058722855882,
            "S": 0.30691789005949754,
            "marginal": 0.003450000000000064
        },
        {
            "K": 64,
            "mean_acc": 0.52655,
            "std_acc": 0.026262568419710978,
            "mean_erank": 15.567918497590522,
            "S": 0.2432487265248519,
            "marginal": 0.0030999999999999917
        },
        {
            "K": 128,
            "mean_acc": 0.54165,
            "std_acc": 0.03117936016020855,
            "mean_erank": 16.236327236888684,
            "S": 0.12684630653819284,
            "marginal": 0.015100000000000002
        },
        {
            "K": 256,
            "mean_acc": 0.5591499999999999,
            "std_acc": 0.029251538421081368,
            "mean_erank": 16.675079919040122,
            "S": 0.06513703093375048,
            "marginal": 0.01749999999999996
        },
        {
            "K": 512,
            "mean_acc": 0.57075,
            "std_acc": 0.03116989733701412,
            "mean_erank": 16.99154631070375,
            "S": 0.03318661388809326,
            "marginal": 0.011600000000000055
        },
        {
            "K": 1024,
            "mean_acc": 0.5818,
            "std_acc": 0.021852002196595166,
            "mean_erank": 17.067000660634946,
            "S": 0.016666992832651314,
            "marginal": 0.011050000000000004
        },
        {
            "K": 2048,
            "mean_acc": 0.59385,
            "std_acc": 0.02599620164562508,
            "mean_erank": 17.12778606152973,
            "S": 0.008363176787856313,
            "marginal": 0.012050000000000005
        },
        {
            "K": 4096,
            "mean_acc": 0.59655,
            "std_acc": 0.02581128629107817,
            "mean_erank": 17.175205013095166,
            "S": 0.004193165286400187,
            "marginal": 0.0027000000000000357
        }
    ]
}